platter.py
platter-1.0.dist-info/DESCRIPTION.rst
platter-1.0.dist-info/METADATA
platter-1.0.dist-info/RECORD
platter-1.0.dist-info/WHEEL
platter-1.0.dist-info/entry_points.txt
platter-1.0.dist-info/metadata.json
platter-1.0.dist-info/top_level.txt
