Metadata-Version: 2.0
Name: platter
Version: 1.0
Summary: A deployment helper for Python.
Home-page: http://github.com/mitsuhiko/platter/
Author: Armin Ronacher
Author-email: armin.ronacher@active-4.com
License: BSD
Platform: any
Requires-Dist: click (>=2.0)
